mypackagepypi/__init__.py
mypackagepypi/log2.py
mypackagepypi/math.py
gmmtest-0.1.0.dist-info/METADATA
gmmtest-0.1.0.dist-info/WHEEL
gmmtest-0.1.0.dist-info/top_level.txt
gmmtest-0.1.0.dist-info/RECORD
