Metadata-Version: 2.1
Name: gmmtest
Version: 0.1.0
Summary: 测试上传pypi.
Home-page: https://github.com/your_username/gmmtest
Author: gmm
Author-email: your.email@example.com
Classifier: Programming Language :: Python :: 3
Classifier: License :: OSI Approved :: MIT License
Classifier: Operating System :: OS Independent
